{
    "name":        "Videos",
    "slug":        "videos",
    "version":     "0.0.3",
    "description": "YouTube and Vimeo embed management with public video grid",
    "author":      "Vertext",
    "category":    "Media",
    "requires":    { "vertext": ">=0.0.2" },
    "nav_routes": [
        {"label": "Videos", "path": "/videos"}
    ],
    "nav": {
        "label":      "Videos",
        "icon":       "pi-video",
        "path":       "/admin/videos",
        "active":     "videos",
        "permission": "videos.view"
    },
    "assets": {
        "css": ["css/videos-front.css"],
        "js":  ["js/videos-front.js"],
        "admin": {
            "css": ["css/videos-admin.css"],
            "js":  ["js/videos-admin.js"]
        }
    }
}
