{
    "name":        "Media",
    "slug":        "media",
    "version":     "0.0.5",
    "description": "General-purpose media library: image upload, management, and picker for use by other modules",
    "author":      "Vertext",
    "category":    "Media",
    "requires":    { "vertext": ">=0.0.1" },
    "assets": {
        "admin": {
            "css": ["css/media.css"],
            "js":  ["js/media.js"]
        }
    },
    "nav": {
        "label":      "Media",
        "icon":       "pi-image",
        "path":       "/admin/media",
        "active":     "media",
        "permission": "media.view"
    }
}
